fedbiomed/__init__.py
fedbiomed/cli.py
fedbiomed/common/__init__.py
fedbiomed/common/certificate_manager.py
fedbiomed/common/channel_manager.py
fedbiomed/common/cli.py
fedbiomed/common/config.py
fedbiomed/common/constants.py
fedbiomed/common/db.py
fedbiomed/common/exceptions.py
fedbiomed/common/ipython.py
fedbiomed/common/json.py
fedbiomed/common/logger.py
fedbiomed/common/message.py
fedbiomed/common/metrics.py
fedbiomed/common/secagg_manager.py
fedbiomed/common/serializer.py
fedbiomed/common/singleton.py
fedbiomed/common/synchro.py
fedbiomed/common/tasks_queue.py
fedbiomed/common/training_args.py
fedbiomed/common/validator.py
fedbiomed/common/data/__init__.py
fedbiomed/common/data/_data_loading_plan.py
fedbiomed/common/data/_data_manager.py
fedbiomed/common/data/_medical_datasets.py
fedbiomed/common/data/_sklearn_data_manager.py
fedbiomed/common/data/_tabular_dataset.py
fedbiomed/common/data/_torch_data_manager.py
fedbiomed/common/data/flamby_dataset.py
fedbiomed/common/models/__init__.py
fedbiomed/common/models/_model.py
fedbiomed/common/models/_sklearn.py
fedbiomed/common/models/_torch.py
fedbiomed/common/optimizers/__init__.py
fedbiomed/common/optimizers/_secagg.py
fedbiomed/common/optimizers/declearn.py
fedbiomed/common/optimizers/generic_optimizers.py
fedbiomed/common/optimizers/optimizer.py
fedbiomed/common/privacy/__init__.py
fedbiomed/common/privacy/_dp_controller.py
fedbiomed/common/secagg/__init__.py
fedbiomed/common/secagg/_additive_ss.py
fedbiomed/common/secagg/_dh.py
fedbiomed/common/secagg/_jls.py
fedbiomed/common/secagg/_lom.py
fedbiomed/common/secagg/_secagg_crypter.py
fedbiomed/common/training_plans/__init__.py
fedbiomed/common/training_plans/_base_training_plan.py
fedbiomed/common/training_plans/_sklearn_models.py
fedbiomed/common/training_plans/_sklearn_models_future.py
fedbiomed/common/training_plans/_sklearn_training_plan.py
fedbiomed/common/training_plans/_torchnn.py
fedbiomed/common/training_plans/_training_iterations.py
fedbiomed-6.1.1.dist-info/METADATA
fedbiomed-6.1.1.dist-info/WHEEL
fedbiomed-6.1.1.dist-info/entry_points.txt
fedbiomed-6.1.1.dist-info/licenses/AUTHORS.md
fedbiomed-6.1.1.dist-info/licenses/LICENSE.md
fedbiomed-6.1.1.dist-info/RECORD
