Metadata-Version: 2.4
Name: fedbiomed
Version: 6.1.1
Summary: Collaborative learning for healthcare
Project-URL: Homepage, https://fedbiomed.org
Project-URL: Documentation, https://fedbiomed.org
Project-URL: Repository, https://github.com/fedbiomed/fedbiomed
Author: Yannick Bouillard <yannick.bouillard@inria.fr>, Francesco Cremonesi <francesco.cremonesi@inria.fr>, Marco Lorenzi <marco.lorenzi@inria.fr>, Paul Andrey <paul.andrey@inria.fr>, Lucie Chambon <lucie.chambon@inria.fr>, Erwan Demairy <erwan.demairy@inria.fr>, Thibaud Kloczko <thibaud.kloczko@inria.fr>, Côme Le Breton <come.le-breton@inria.fr>, Jean-Luc Szpyrka <jean-luc@szpyrka.fr>, Riccardo Taiello <riccardo.taiello@inria.fr>, Maya Assal, Samy-Safwan Ayed, Irene Balelli, Nathan Bigaud, Eleo
Author-email: Sergen Cansiz <sergen.cansiz@inria.fr>, Marc Vesin <marc.vesin@inria.fr>
Maintainer: Yannick Bouillard <yannick.bouillard@inria.fr>, Francesco Cremonesi <francesco.cremonesi@inria.fr>, Marco Lorenzi <marco.lorenzi@inria.fr>
Maintainer-email: Sergen Cansiz <sergen.cansiz@inria.fr>, Marc Vesin <marc.vesin@inria.fr>
License: Apache 2.0
License-File: AUTHORS.md
License-File: LICENSE.md
Keywords: ai,analytics,biomedical,clinical,collaborative,federated,healthcare,learning,multicentric
Classifier: Development Status :: 5 - Production/Stable
Classifier: Intended Audience :: Healthcare Industry
Classifier: Intended Audience :: Science/Research
Classifier: License :: OSI Approved :: Apache Software License
Classifier: Natural Language :: English
Classifier: Operating System :: MacOS
Classifier: Operating System :: Unix
Classifier: Programming Language :: Python :: 3
Classifier: Topic :: Scientific/Engineering :: Artificial Intelligence
Requires-Python: <3.11,>=3.10
Requires-Dist: cryptography~=40.0
Requires-Dist: declearn[torch1]~=2.6.0
Requires-Dist: gmpy2<2.2,>=2.1
Requires-Dist: grpcio-tools~=1.66
Requires-Dist: grpcio~=1.66
Requires-Dist: itk~=5.3
Requires-Dist: joblib~=1.2
Requires-Dist: monai<1.2.0,>=1.1.0
Requires-Dist: msgpack~=1.0
Requires-Dist: opacus<1.4.1,>=1.4.0
Requires-Dist: packaging~=24.1
Requires-Dist: pandas~=2.0.1
Requires-Dist: persist-queue<0.6.0,>=0.5.1
Requires-Dist: psutil~=6.0.0
Requires-Dist: pygments~=2.18.0
Requires-Dist: pyopenssl~=23.1.1
Requires-Dist: python-minifier~=2.11
Requires-Dist: requests~=2.29
Requires-Dist: scikit-learn<1.3.0,>=1.2.0
Requires-Dist: scipy<1.11.0,>=1.10.0
Requires-Dist: tabulate<0.10.0,>=0.9.0
Requires-Dist: tinydb~=4.7.1
Requires-Dist: torchvision<0.15.0,>=0.14.0
Requires-Dist: torch~=1.13.0
Requires-Dist: unet<0.8.0,>=0.7.7
Requires-Dist: validators<0.21.0,>=0.20.0
Provides-Extra: gui
Requires-Dist: cachelib<0.11.0,>=0.10.2; extra == 'gui'
Requires-Dist: flask-jwt-extended<4.5.0,>=4.4.4; extra == 'gui'
Requires-Dist: flask<24.0,>=2.3.1; extra == 'gui'
Requires-Dist: gunicorn~=23.0.0; extra == 'gui'
Requires-Dist: jsonschema~=4.18.0; extra == 'gui'
Provides-Extra: node
Provides-Extra: researcher
Requires-Dist: ipython; extra == 'researcher'
Requires-Dist: jupyter; extra == 'researcher'
Requires-Dist: matplotlib<3.8.4,>=3.8.0; extra == 'researcher'
Requires-Dist: pathvalidate~=3.0.0; extra == 'researcher'
Requires-Dist: tensorboard~=2.18.0; extra == 'researcher'
